odoo/addons/web_widget_url_translatable/README.rst
odoo/addons/web_widget_url_translatable/__init__.py
odoo/addons/web_widget_url_translatable/__manifest__.py
odoo/addons/web_widget_url_translatable/i18n/ca.po
odoo/addons/web_widget_url_translatable/i18n/es.po
odoo/addons/web_widget_url_translatable/i18n/pt_BR.po
odoo/addons/web_widget_url_translatable/i18n/web_widget_url_translatable.pot
odoo/addons/web_widget_url_translatable/readme/CONTRIBUTORS.rst
odoo/addons/web_widget_url_translatable/readme/DESCRIPTION.rst
odoo/addons/web_widget_url_translatable/static/description/icon.png
odoo/addons/web_widget_url_translatable/static/description/index.html
odoo/addons/web_widget_url_translatable/static/src/js/fields.js
odoo/addons/web_widget_url_translatable/views/assets.xml
odoo12_addon_web_widget_url_translatable-12.0.1.0.0.99.dev11.dist-info/METADATA
odoo12_addon_web_widget_url_translatable-12.0.1.0.0.99.dev11.dist-info/WHEEL
odoo12_addon_web_widget_url_translatable-12.0.1.0.0.99.dev11.dist-info/top_level.txt
odoo12_addon_web_widget_url_translatable-12.0.1.0.0.99.dev11.dist-info/RECORD
